setup.py
gaus_bino_dist/Binomialdistribution.py
gaus_bino_dist/Gaussiandistribution.py
gaus_bino_dist/Generaldistribution.py
gaus_bino_dist/__init__.py
gaus_bino_dist.egg-info/PKG-INFO
gaus_bino_dist.egg-info/SOURCES.txt
gaus_bino_dist.egg-info/dependency_links.txt
gaus_bino_dist.egg-info/not-zip-safe
gaus_bino_dist.egg-info/top_level.txt