Metadata-Version: 1.0
Name: gaus-bino-dist
Version: 1.0
Summary: Gaussian and Binomial distributions
Home-page: UNKNOWN
Author: Maitrey Talware
Author-email: UNKNOWN
License: UNKNOWN
Platform: UNKNOWN
